is_troo/__init__.py
is_troo/analyzers.py
is_troo/eval.py
is_troo/exceptions.py
is_troo-1.0.1.dist-info/licenses/LICENSE
is_troo-1.0.1.dist-info/METADATA
is_troo-1.0.1.dist-info/WHEEL
is_troo-1.0.1.dist-info/top_level.txt
is_troo-1.0.1.dist-info/RECORD
