Metadata-Version: 2.4
Name: is_troo
Version: 1.0.1
Summary: The only package you'll ever need for finally figuring out what that expression evals to!
Author-email: Axo <benjaminvpage@gmail.com>
License-Expression: MIT
Project-URL: Homepage, https://github.com/w0termel0n/is-troo
Keywords: truth,truthy,trooth
Classifier: Programming Language :: Python :: 3
Classifier: Operating System :: OS Independent
Requires-Python: >=3.8
License-File: LICENSE
Dynamic: license-file
